liminal/__init__.py
liminal/atuin-installer.sh
liminal/atuin.py
liminal/cli.py
liminal/command_runner.py
liminal/config.py
liminal/datetime_util.py
liminal/env.py
liminal/filesystem.py
liminal/installer.py
liminal/logging.py
liminal/session.py
liminal/shell-extension_template.txt
liminal/shell-rc_load-extension_template.txt
liminal/shell.py
liminal/commands/__init__.py
liminal/commands/shell.py
liminal_cli-0.7.3.dist-info/METADATA
liminal_cli-0.7.3.dist-info/WHEEL
liminal_cli-0.7.3.dist-info/entry_points.txt
liminal_cli-0.7.3.dist-info/top_level.txt
liminal_cli-0.7.3.dist-info/RECORD
