Metadata-Version: 2.4
Name: liminal-cli
Version: 0.7.3
Summary: Liminal CLI and tools
Author-email: Dev <devs@liminalbios.com>
Requires-Python: >=3.10
Requires-Dist: requests==2.32.*
Requires-Dist: psutil==7.0.*
Requires-Dist: tomlkit==0.13.3
Requires-Dist: typer==0.16.0
Requires-Dist: pexpect==4.9.0
